Prihops.py
prihops-0.5.dist-info/licenses/LICENSE
prihops-0.5.dist-info/METADATA
prihops-0.5.dist-info/WHEEL
prihops-0.5.dist-info/top_level.txt
prihops-0.5.dist-info/RECORD
