Metadata-Version: 2.4
Name: Prihops
Version: 0.5
Summary: Google drive integration
Home-page: 
Author: Bedirhan
Author-email: bedirhan.oytpass@gmail.com
Keywords: Google,DRİVE,entegration
Classifier: Programming Language :: Python :: 3
Classifier: License :: Other/Proprietary License
Classifier: Operating System :: OS Independent
License-File: LICENSE
Requires-Dist: tkinter
Requires-Dist: google-auth
Requires-Dist: google-api-python-client
Requires-Dist: google-auth-httplib2
Requires-Dist: google-auth-oauthlib
Requires-Dist: Pillow
Dynamic: author
Dynamic: author-email
Dynamic: classifier
Dynamic: description
Dynamic: description-content-type
Dynamic: keywords
Dynamic: license-file
Dynamic: requires-dist
Dynamic: summary
